ohsome2label/__init__.py
ohsome2label/config.py
ohsome2label/label.py
ohsome2label/main.py
ohsome2label/overpass.py
ohsome2label/palette.py
ohsome2label/polygon-features.json
ohsome2label/quality.py
ohsome2label/readme.md
ohsome2label/tile.py
ohsome2label/utils.py
ohsome2label/visualize.py
ohsome2label-1.1.3.dist-info/LICENSE.txt
ohsome2label-1.1.3.dist-info/METADATA
ohsome2label-1.1.3.dist-info/WHEEL
ohsome2label-1.1.3.dist-info/entry_points.txt
ohsome2label-1.1.3.dist-info/top_level.txt
ohsome2label-1.1.3.dist-info/RECORD
