Metadata-Version: 2.1
Name: ohsome2label
Version: 1.1.3
Summary: Historical OpenStreetMap Objects
Home-page: https://github.com/GIScience/ohsome2label
Author: Zhaoyan Wu, Hao Li
Author-email: zhaoyan_wu@whu.edu.cn, hao.li@uni-heidelberg.de
License: MIT
Platform: UNKNOWN
Classifier: Intended Audience :: Developers
Classifier: License :: OSI Approved :: MIT License
Classifier: Programming Language :: Python :: 3.6
Requires-Python: >=3.6
License-File: LICENSE.txt
Requires-Dist: numpy (==1.17.3)
Requires-Dist: gevent (==1.4.0)
Requires-Dist: click (==7.0)
Requires-Dist: pykwalify (==1.7.0)
Requires-Dist: shapely (==1.6.4)
Requires-Dist: tqdm (==4.38.0)
Requires-Dist: Pillow (>=7.1.0)
Requires-Dist: requests (==2.22.0)
Requires-Dist: geojson (==2.5.0)
Requires-Dist: matplotlib (==3.2.2)
